[
  {
    "title": "河北省注册会计师协会关于择优推荐会计师事务所参与《中",
    "url": "https://law.esnai.cn/view/233577/",
    "source": "中国会计视野",
    "category": "policy",
    "publishedAt": "2026-07-09"
  },
  {
    "title": "天津市资产评估协会关于做好最高法入库机构信息变更有关",
    "url": "https://law.esnai.cn/view/233562/",
    "source": "中国会计视野",
    "category": "policy",
    "publishedAt": "2026-07-09"
  },
  {
    "title": "河南省注册会计师协会关于开展2026年会计师事务所执业质",
    "url": "https://law.esnai.cn/view/233570/",
    "source": "中国会计视野",
    "category": "policy",
    "publishedAt": "2026-07-09"
  },
  {
    "title": "湖北省注册会计师协会关于开展2026年全省会计师事务所执",
    "url": "https://law.esnai.cn/view/233569/",
    "source": "中国会计视野",
    "category": "policy",
    "publishedAt": "2026-07-09"
  },
  {
    "title": "关于《海关总署关于实施中国-乌兹别克斯坦海关“经认证的",
    "url": "https://law.esnai.cn/view/233566/",
    "source": "中国会计视野",
    "category": "policy",
    "publishedAt": "2026-07-09"
  },
  {
    "title": "内蒙古自治区财政厅关于开展2026年度会计师事务所和资产",
    "url": "https://law.esnai.cn/view/233579/",
    "source": "中国会计视野",
    "category": "policy",
    "publishedAt": "2026-07-09"
  },
  {
    "title": "关于开展《中国注册会计师业务指导目录2026》编写工作的",
    "url": "https://law.esnai.cn/view/233578/",
    "source": "中国会计视野",
    "category": "policy",
    "publishedAt": "2026-07-09"
  },
  {
    "title": "浙江省注册会计师协会关于开展2026年全省会计师事务所执",
    "url": "https://law.esnai.cn/view/233576/",
    "source": "中国会计视野",
    "category": "policy",
    "publishedAt": "2026-07-09"
  },
  {
    "title": "浙江省注册会计师协会关于开展2026年度会员疗休养工作的",
    "url": "https://law.esnai.cn/view/233575/",
    "source": "中国会计视野",
    "category": "policy",
    "publishedAt": "2026-07-09"
  },
  {
    "title": "浙江省资产评估协会关于开展2026年全省资产评估行业执业",
    "url": "https://law.esnai.cn/view/233574/",
    "source": "中国会计视野",
    "category": "policy",
    "publishedAt": "2026-07-09"
  },
  {
    "title": "国家税务总局北京市税务局北京市人力资源和社会保障局北",
    "url": "https://law.esnai.cn/view/232852/",
    "source": "中国会计视野",
    "category": "policy",
    "publishedAt": "2026-07-09"
  },
  {
    "title": "关于在成品油零售领域全面推广“交易即开票”有关事项的",
    "url": "https://law.esnai.cn/view/232896/",
    "source": "中国会计视野",
    "category": "policy",
    "publishedAt": "2026-07-09"
  },
  {
    "title": "关于发布《公开募集证券投资基金主题投资风格管理指引》",
    "url": "https://law.esnai.cn/view/232933/",
    "source": "中国会计视野",
    "category": "policy",
    "publishedAt": "2026-07-09"
  },
  {
    "title": "国家税务总局深圳市税务局12366每周咨询热点[20260608-2",
    "url": "https://law.esnai.cn/view/233026/",
    "source": "中国会计视野",
    "category": "policy",
    "publishedAt": "2026-07-09"
  },
  {
    "title": "关于开展2026年全国会计师事务所执业质量检查工作的通知",
    "url": "https://law.esnai.cn/view/233045/",
    "source": "中国会计视野",
    "category": "policy",
    "publishedAt": "2026-07-09"
  },
  {
    "title": "关于银行业保险业人工智能安全开发应用的指导意见",
    "url": "https://law.esnai.cn/view/233057/",
    "source": "中国会计视野",
    "category": "policy",
    "publishedAt": "2026-07-09"
  },
  {
    "title": "国家税务总局上海市税务局合规开具发票热点问答",
    "url": "https://law.esnai.cn/view/232891/",
    "source": "中国会计视野",
    "category": "policy",
    "publishedAt": "2026-07-09"
  },
  {
    "title": "国家税务总局江苏省税务局12366热点问答[2026年5月]",
    "url": "https://law.esnai.cn/view/233028/",
    "source": "中国会计视野",
    "category": "policy",
    "publishedAt": "2026-07-09"
  },
  {
    "title": "国家税务总局河南省税务局12366热线2026年5月热点问题",
    "url": "https://law.esnai.cn/view/232907/",
    "source": "中国会计视野",
    "category": "policy",
    "publishedAt": "2026-07-09"
  },
  {
    "title": "国家税务总局四川省税务局关于公布全文和部分条款废止的",
    "url": "https://law.esnai.cn/view/232936/",
    "source": "中国会计视野",
    "category": "policy",
    "publishedAt": "2026-07-09"
  }
]